README.md
setup.py
trend_analyzer/__init__.py
trend_analyzer/analyzer.py
trend_analyzer/llms.py
trend_analyzer/prompt_template.txt
trend_analyzer/tools.py
trend_analyzer/vectorstore.py
trend_analyzer.egg-info/PKG-INFO
trend_analyzer.egg-info/SOURCES.txt
trend_analyzer.egg-info/dependency_links.txt
trend_analyzer.egg-info/entry_points.txt
trend_analyzer.egg-info/requires.txt
trend_analyzer.egg-info/top_level.txt
trend_analyzer/entrypoints/__init__.py
trend_analyzer/entrypoints/cli.py
trend_analyzer/entrypoints/server.py
trend_analyzer/files/sample-search.json
trend_analyzer/files/sample-youtube.json